fib_payments/__init__.py
fib_payments/async_http_utils.py
fib_payments/client.py
fib_payments/config.py
fib_payments/exceptions.py
fib_python_payment_sdk-0.4.0.dist-info/LICENSE
fib_python_payment_sdk-0.4.0.dist-info/METADATA
fib_python_payment_sdk-0.4.0.dist-info/WHEEL
fib_python_payment_sdk-0.4.0.dist-info/top_level.txt
fib_python_payment_sdk-0.4.0.dist-info/RECORD
