Metadata-Version: 2.1
Name: fib-python-payment-sdk
Version: 0.4.0
Summary: SDK for integrating with the FIB payment system, enabling user authentication and payment transactions.
Home-page: https://the-gw.com/
Author: Gateway ICT
Author-email: info@the-gw.com
License: MIT
Keywords: sdk,fib,payment,integration
Platform: UNKNOWN
Classifier: Development Status :: 3 - Alpha
Classifier: Intended Audience :: Developers
Classifier: License :: OSI Approved :: MIT License
Classifier: Programming Language :: Python :: 3
Classifier: Programming Language :: Python :: 3.7
Classifier: Programming Language :: Python :: 3.8
Classifier: Programming Language :: Python :: 3.9
Requires-Python: >=3.7, <4
Requires-Dist: httpx<1.0.0,>=0.27.0
Provides-Extra: dev
Requires-Dist: pytest>=6.0.0; extra == "dev"
